pyside_app_build/__init__.py
pyside_app_build/_custom_icon_gen.py
pyside_app_build/_exception.py
pyside_app_build/_pysidedeploy_spec_gen.py
pyside_app_build/build_hook.py
pyside_app_build/builder.py
pyside_app_build/config.py
pyside_app_build/constants.py
pyside_app_build/hooks.py
pyside_app_build/resource_generator/__init__.py
pyside_app_build/resource_generator/__main__.py
pyside_app_build/resource_generator/generate_resources.py
pyside_app_build/resource_generator/resource_types.py
pyside_app_build/resources/dmg_background.png
pyside_app_build/templates/finder_tweaks.scpt.jinja2
pyside_app_build/templates/resources.qrc.jinja2
pyside_app_core/__about__.py
pyside_app_core/__init__.py
pyside_app_core/_version.py
pyside_app_core/constants.py
pyside_app_core/py.typed
pyside_app_core/app/__init__.py
pyside_app_core/app/application_service.py
pyside_app_core/errors/__init__.py
pyside_app_core/errors/basic_errors.py
pyside_app_core/errors/encode_errors.py
pyside_app_core/errors/excepthook.py
pyside_app_core/errors/serial_errors.py
pyside_app_core/log/__init__.py
pyside_app_core/mixin/__init__.py
pyside_app_core/mixin/object_name_mixin.py
pyside_app_core/mixin/settings_mixin.py
pyside_app_core/resources/__init__.py
pyside_app_core/resources/core/iconoir/_LICENSE.txt
pyside_app_core/resources/core/iconoir/_README.md
pyside_app_core/resources/core/iconoir/ev-plug-charging.svg
pyside_app_core/resources/core/iconoir/ev-plug-xmark.svg
pyside_app_core/resources/core/iconoir/ev-plug.svg
pyside_app_core/resources/core/iconoir/floppy-disk-arrow-in.svg
pyside_app_core/resources/core/iconoir/floppy-disk-arrow-out.svg
pyside_app_core/resources/core/iconoir/floppy-disk.svg
pyside_app_core/resources/core/iconoir/folder-warning.svg
pyside_app_core/resources/core/iconoir/folder.svg
pyside_app_core/resources/core/iconoir/open-new-window.svg
pyside_app_core/resources/core/iconoir/page-edit.svg
pyside_app_core/resources/core/iconoir/page-plus-in.svg
pyside_app_core-0.14.4.dist-info/METADATA
pyside_app_core-0.14.4.dist-info/WHEEL
pyside_app_core-0.14.4.dist-info/entry_points.txt
pyside_app_core-0.14.4.dist-info/licenses/LICENSE
pyside_app_core-0.14.4.dist-info/RECORD
