Metadata-Version: 2.3
Name: pyside-app-core
Version: 0.14.4
Summary: Framework for PySide6 Applications
Project-URL: Source, https://github.com/leocov-dev/pyside-app-core
Project-URL: Issues, https://github.com/leocov-dev/pyside-app-core/issues
Project-URL: Releases, https://github.com/leocov-dev/pyside-app-core/releases
Author-email: Leo Covarrubias <leo@leocov.com>
Keywords: framework,pyside,pyside6,qt,qt6
Classifier: Development Status :: 2 - Pre-Alpha
Classifier: Intended Audience :: Developers
Classifier: License :: OSI Approved :: GNU Lesser General Public License v3 or later (LGPLv3+)
Classifier: Programming Language :: Python
Classifier: Programming Language :: Python :: 3
Classifier: Topic :: Desktop Environment
Classifier: Topic :: Software Development :: Libraries :: Python Modules
Classifier: Typing :: Typed
Requires-Python: >=3.12
Requires-Dist: hatchling
Requires-Dist: jinja2==3.*
Requires-Dist: loguru
Requires-Dist: pyside6>=6.8
Requires-Dist: typing-extensions
